kola-2.2.0.dist-info/METADATA
kola-2.2.0.dist-info/WHEEL
kola-2.2.0.dist-info/licenses/LICENSE
kola.libs/libcom_err-2abe824b.so.2
kola.libs/libcrypto-d3570994.so.10
kola.libs/libgssapi_krb5-497db0c6.so.2
kola.libs/libk5crypto-b1f99d5c.so.3
kola.libs/libkeyutils-dfe70bd6.so.1
kola.libs/libkrb5-fcafa220.so.3
kola.libs/libkrb5support-d0bcff84.so.0
kola.libs/libpcre-9513aab5.so.1
kola.libs/libselinux-0922c95c.so.1
kola.libs/libssl-cd1d6220.so.10
kola/__init__.py
kola/exceptions.py
kola/j.py
kola/kola.cpython-314-x86_64-linux-gnu.so
kola/py.typed
kola/q.py
kola/type.py
kola/util.py
rust-toolchain.toml
kola-2.2.0.dist-info/RECORD
