Metadata-Version: 2.4
Name: kola
Version: 2.2.0
Classifier: Programming Language :: Python :: 3
Classifier: Programming Language :: Python :: 3 :: Only
Classifier: Programming Language :: Python :: 3.10
Classifier: Programming Language :: Python :: 3.11
Classifier: Programming Language :: Python :: 3.12
Classifier: Programming Language :: Python :: 3.13
Classifier: Programming Language :: Rust
Requires-Dist: polars>=1.31.0
Requires-Dist: pyarrow>=20.0.0
License-File: LICENSE
Summary: a Python Polars interface to j* and q
Keywords: j*,q,kdb,polars,dataframe,arrow
Author-email: Jo Shinonome <jo.shinonome@gmail.com>
Requires-Python: >=3.10
Project-URL: Repository, https://github.com/jshinonome/kola
